LICENSE.txt
README.md
setup.cfg
setup.py
SinusoidalWaves/Waves.py
SinusoidalWaves/__init__.py
SinusoidalWaves.egg-info/PKG-INFO
SinusoidalWaves.egg-info/SOURCES.txt
SinusoidalWaves.egg-info/dependency_links.txt
SinusoidalWaves.egg-info/requires.txt
SinusoidalWaves.egg-info/top_level.txt