Metadata-Version: 2.1
Name: SinusoidalWaves
Version: 1.0.0
Summary: Contains Sine and Cosine classes for generating and transforming sinusoidal waves.
Home-page: https://github.com/TylerBurgee/SinusoidalWaves
Download-URL: https://github.com/TylerBurgee/SinusoidalWaves/archive/refs/tags/v1.0.0.tar.gz
Author: Tyler Burgee
Author-email: tylerburgee@gmail.com
License: MIT
Keywords: waves,sine,cosine,transformation,signal,processing
Classifier: Development Status :: 5 - Production/Stable
Classifier: Intended Audience :: Developers
Classifier: Topic :: Software Development :: Build Tools
Classifier: License :: OSI Approved :: MIT License
Classifier: Programming Language :: Python :: 3
Classifier: Programming Language :: Python :: 3.4
Classifier: Programming Language :: Python :: 3.5
Classifier: Programming Language :: Python :: 3.6
Classifier: Programming Language :: Python :: 3.7
Classifier: Programming Language :: Python :: 3.8
Classifier: Programming Language :: Python :: 3.9
Classifier: Programming Language :: Python :: 3.10
Classifier: Programming Language :: Python :: 3.11
License-File: LICENSE.txt
